SARepo/__init__.py
SARepo/base.py
SARepo/models.py
SARepo/repo.py
SARepo/sa_repo.py
SARepo/specs.py
SARepo/uow.py
sarepo-0.1.8.dist-info/licenses/LICENSE
sarepo-0.1.8.dist-info/METADATA
sarepo-0.1.8.dist-info/WHEEL
sarepo-0.1.8.dist-info/top_level.txt
sarepo-0.1.8.dist-info/RECORD
