Metadata-Version: 2.4
Name: SARepo
Version: 0.1.8
Summary: Minimal, explicit Repository & Unit-of-Work layer over SQLAlchemy 2.x
Author: nurbergenovv
License: MIT
Requires-Python: >=3.11
License-File: LICENSE
Requires-Dist: SQLAlchemy>=2.0
Dynamic: license-file
